[{"year":1976,"origin":"domestic","total_inventors":73722,"female_inventors":2160.0,"female_share_pct":2.93},{"year":1976,"origin":"foreign_origin","total_inventors":42114,"female_inventors":1093.0,"female_share_pct":2.6},{"year":1977,"origin":"domestic","total_inventors":68987,"female_inventors":2155.0,"female_share_pct":3.12},{"year":1977,"origin":"foreign_origin","total_inventors":39152,"female_inventors":933.0,"female_share_pct":2.38},{"year":1978,"origin":"domestic","total_inventors":69393,"female_inventors":2302.0,"female_share_pct":3.32},{"year":1978,"origin":"foreign_origin","total_inventors":41378,"female_inventors":1114.0,"female_share_pct":2.69},{"year":1979,"origin":"domestic","total_inventors":51357,"female_inventors":1806.0,"female_share_pct":3.52},{"year":1979,"origin":"foreign_origin","total_inventors":31579,"female_inventors":847.0,"female_share_pct":2.68},{"year":1980,"origin":"domestic","total_inventors":63814,"female_inventors":2321.0,"female_share_pct":3.64},{"year":1980,"origin":"foreign_origin","total_inventors":41578,"female_inventors":1190.0,"female_share_pct":2.86},{"year":1981,"origin":"domestic","total_inventors":66793,"female_inventors":2463.0,"female_share_pct":3.69},{"year":1981,"origin":"foreign_origin","total_inventors":46579,"female_inventors":1372.0,"female_share_pct":2.95},{"year":1982,"origin":"domestic","total_inventors":57263,"female_inventors":2092.0,"female_share_pct":3.65},{"year":1982,"origin":"foreign_origin","total_inventors":43061,"female_inventors":1322.0,"female_share_pct":3.07},{"year":1983,"origin":"domestic","total_inventors":55839,"female_inventors":2205.0,"female_share_pct":3.95},{"year":1983,"origin":"foreign_origin","total_inventors":43724,"female_inventors":1233.0,"female_share_pct":2.82},{"year":1984,"origin":"domestic","total_inventors":65921,"female_inventors":2798.0,"female_share_pct":4.24},{"year":1984,"origin":"foreign_origin","total_inventors":52654,"female_inventors":1561.0,"female_share_pct":2.96},{"year":1985,"origin":"domestic","total_inventors":69326,"female_inventors":3005.0,"female_share_pct":4.33},{"year":1985,"origin":"foreign_origin","total_inventors":58547,"female_inventors":1732.0,"female_share_pct":2.96},{"year":1986,"origin":"domestic","total_inventors":67301,"female_inventors":3094.0,"female_share_pct":4.6},{"year":1986,"origin":"foreign_origin","total_inventors":59491,"female_inventors":1830.0,"female_share_pct":3.08},{"year":1987,"origin":"domestic","total_inventors":78314,"female_inventors":3773.0,"female_share_pct":4.82},{"year":1987,"origin":"foreign_origin","total_inventors":73707,"female_inventors":2393.0,"female_share_pct":3.25},{"year":1988,"origin":"domestic","total_inventors":74793,"female_inventors":3936.0,"female_share_pct":5.26},{"year":1988,"origin":"foreign_origin","total_inventors":72285,"female_inventors":2478.0,"female_share_pct":3.43},{"year":1989,"origin":"domestic","total_inventors":94488,"female_inventors":5507.0,"female_share_pct":5.83},{"year":1989,"origin":"foreign_origin","total_inventors":89278,"female_inventors":3320.0,"female_share_pct":3.72},{"year":1990,"origin":"domestic","total_inventors":91614,"female_inventors":5645.0,"female_share_pct":6.16},{"year":1990,"origin":"foreign_origin","total_inventors":85749,"female_inventors":3435.0,"female_share_pct":4.01},{"year":1991,"origin":"domestic","total_inventors":100155,"female_inventors":6479.0,"female_share_pct":6.47},{"year":1991,"origin":"foreign_origin","total_inventors":90715,"female_inventors":3777.0,"female_share_pct":4.16},{"year":1992,"origin":"domestic","total_inventors":105545,"female_inventors":7141.0,"female_share_pct":6.77},{"year":1992,"origin":"foreign_origin","total_inventors":91900,"female_inventors":4252.0,"female_share_pct":4.63},{"year":1993,"origin":"domestic","total_inventors":111062,"female_inventors":7587.0,"female_share_pct":6.83},{"year":1993,"origin":"foreign_origin","total_inventors":93329,"female_inventors":4485.0,"female_share_pct":4.81},{"year":1994,"origin":"domestic","total_inventors":119430,"female_inventors":8446.0,"female_share_pct":7.07},{"year":1994,"origin":"foreign_origin","total_inventors":93440,"female_inventors":4525.0,"female_share_pct":4.84},{"year":1995,"origin":"domestic","total_inventors":121383,"female_inventors":8826.0,"female_share_pct":7.27},{"year":1995,"origin":"foreign_origin","total_inventors":93867,"female_inventors":5092.0,"female_share_pct":5.42},{"year":1996,"origin":"domestic","total_inventors":137992,"female_inventors":10777.0,"female_share_pct":7.81},{"year":1996,"origin":"foreign_origin","total_inventors":101521,"female_inventors":5879.0,"female_share_pct":5.79},{"year":1997,"origin":"domestic","total_inventors":143214,"female_inventors":11875.0,"female_share_pct":8.29},{"year":1997,"origin":"foreign_origin","total_inventors":105298,"female_inventors":6638.0,"female_share_pct":6.3},{"year":1998,"origin":"domestic","total_inventors":190389,"female_inventors":16301.0,"female_share_pct":8.56},{"year":1998,"origin":"foreign_origin","total_inventors":137479,"female_inventors":9207.0,"female_share_pct":6.7},{"year":1999,"origin":"domestic","total_inventors":201646,"female_inventors":18057.0,"female_share_pct":8.95},{"year":1999,"origin":"foreign_origin","total_inventors":139237,"female_inventors":9552.0,"female_share_pct":6.86},{"year":2000,"origin":"domestic","total_inventors":208629,"female_inventors":18595.0,"female_share_pct":8.91},{"year":2000,"origin":"foreign_origin","total_inventors":146102,"female_inventors":10012.0,"female_share_pct":6.85},{"year":2001,"origin":"domestic","total_inventors":220413,"female_inventors":20461.0,"female_share_pct":9.28},{"year":2001,"origin":"foreign_origin","total_inventors":159587,"female_inventors":11064.0,"female_share_pct":6.93},{"year":2002,"origin":"domestic","total_inventors":211203,"female_inventors":19186.0,"female_share_pct":9.08},{"year":2002,"origin":"foreign_origin","total_inventors":154203,"female_inventors":10530.0,"female_share_pct":6.83},{"year":2003,"origin":"domestic","total_inventors":222309,"female_inventors":20480.0,"female_share_pct":9.21},{"year":2003,"origin":"foreign_origin","total_inventors":158479,"female_inventors":11171.0,"female_share_pct":7.05},{"year":2004,"origin":"domestic","total_inventors":223750,"female_inventors":21322.0,"female_share_pct":9.53},{"year":2004,"origin":"foreign_origin","total_inventors":161538,"female_inventors":11819.0,"female_share_pct":7.32},{"year":2005,"origin":"domestic","total_inventors":199039,"female_inventors":19004.0,"female_share_pct":9.55},{"year":2005,"origin":"foreign_origin","total_inventors":139830,"female_inventors":10574.0,"female_share_pct":7.56},{"year":2006,"origin":"domestic","total_inventors":246582,"female_inventors":23714.0,"female_share_pct":9.62},{"year":2006,"origin":"foreign_origin","total_inventors":168901,"female_inventors":13629.0,"female_share_pct":8.07},{"year":2007,"origin":"domestic","total_inventors":225132,"female_inventors":22093.0,"female_share_pct":9.81},{"year":2007,"origin":"foreign_origin","total_inventors":155354,"female_inventors":13557.0,"female_share_pct":8.73},{"year":2008,"origin":"domestic","total_inventors":226429,"female_inventors":22788.0,"female_share_pct":10.06},{"year":2008,"origin":"foreign_origin","total_inventors":157345,"female_inventors":14341.0,"female_share_pct":9.11},{"year":2009,"origin":"domestic","total_inventors":245184,"female_inventors":24903.0,"female_share_pct":10.16},{"year":2009,"origin":"foreign_origin","total_inventors":166472,"female_inventors":16006.0,"female_share_pct":9.61},{"year":2010,"origin":"domestic","total_inventors":324740,"female_inventors":33435.0,"female_share_pct":10.3},{"year":2010,"origin":"foreign_origin","total_inventors":223519,"female_inventors":23082.0,"female_share_pct":10.33},{"year":2011,"origin":"domestic","total_inventors":329587,"female_inventors":34225.0,"female_share_pct":10.38},{"year":2011,"origin":"foreign_origin","total_inventors":234317,"female_inventors":25095.0,"female_share_pct":10.71},{"year":2012,"origin":"domestic","total_inventors":368100,"female_inventors":38607.0,"female_share_pct":10.49},{"year":2012,"origin":"foreign_origin","total_inventors":268636,"female_inventors":29361.0,"female_share_pct":10.93},{"year":2013,"origin":"domestic","total_inventors":410524,"female_inventors":43268.0,"female_share_pct":10.54},{"year":2013,"origin":"foreign_origin","total_inventors":298957,"female_inventors":34647.0,"female_share_pct":11.59},{"year":2014,"origin":"domestic","total_inventors":450474,"female_inventors":47997.0,"female_share_pct":10.65},{"year":2014,"origin":"foreign_origin","total_inventors":320101,"female_inventors":37863.0,"female_share_pct":11.83},{"year":2015,"origin":"domestic","total_inventors":445636,"female_inventors":47377.0,"female_share_pct":10.63},{"year":2015,"origin":"foreign_origin","total_inventors":324096,"female_inventors":39234.0,"female_share_pct":12.11},{"year":2016,"origin":"domestic","total_inventors":458283,"female_inventors":49520.0,"female_share_pct":10.81},{"year":2016,"origin":"foreign_origin","total_inventors":326701,"female_inventors":41049.0,"female_share_pct":12.56},{"year":2017,"origin":"domestic","total_inventors":486759,"female_inventors":53490.0,"female_share_pct":10.99},{"year":2017,"origin":"foreign_origin","total_inventors":346965,"female_inventors":44555.0,"female_share_pct":12.84},{"year":2018,"origin":"domestic","total_inventors":469494,"female_inventors":52468.0,"female_share_pct":11.18},{"year":2018,"origin":"foreign_origin","total_inventors":338961,"female_inventors":44266.0,"female_share_pct":13.06},{"year":2019,"origin":"domestic","total_inventors":551251,"female_inventors":62530.0,"female_share_pct":11.34},{"year":2019,"origin":"foreign_origin","total_inventors":389032,"female_inventors":51987.0,"female_share_pct":13.36},{"year":2020,"origin":"domestic","total_inventors":558073,"female_inventors":65107.0,"female_share_pct":11.67},{"year":2020,"origin":"foreign_origin","total_inventors":388320,"female_inventors":54198.0,"female_share_pct":13.96},{"year":2021,"origin":"domestic","total_inventors":517069,"female_inventors":63854.0,"female_share_pct":12.35},{"year":2021,"origin":"foreign_origin","total_inventors":369500,"female_inventors":53795.0,"female_share_pct":14.56},{"year":2022,"origin":"domestic","total_inventors":494454,"female_inventors":62276.0,"female_share_pct":12.59},{"year":2022,"origin":"foreign_origin","total_inventors":378776,"female_inventors":57862.0,"female_share_pct":15.28},{"year":2023,"origin":"domestic","total_inventors":537601,"female_inventors":69720.0,"female_share_pct":12.97},{"year":2023,"origin":"foreign_origin","total_inventors":326463,"female_inventors":51190.0,"female_share_pct":15.68},{"year":2024,"origin":"domestic","total_inventors":522358,"female_inventors":70943.0,"female_share_pct":13.58},{"year":2024,"origin":"foreign_origin","total_inventors":378682,"female_inventors":58957.0,"female_share_pct":15.57},{"year":2025,"origin":"domestic","total_inventors":385487,"female_inventors":53123.0,"female_share_pct":13.78},{"year":2025,"origin":"foreign_origin","total_inventors":294694,"female_inventors":48474.0,"female_share_pct":16.45}]