[{"cpc_section":"A","total_patents":583532,"sleeping_beauties":227834.0,"sb_rate_pct":39.044,"mean_half_life":13.05,"median_half_life":12.0,"n_patents":452948,"section_name":"Human Necessities"},{"cpc_section":"B","total_patents":691527,"sleeping_beauties":215038.0,"sb_rate_pct":31.096,"mean_half_life":12.33,"median_half_life":11.0,"n_patents":480297,"section_name":"Operations & Transport"},{"cpc_section":"C","total_patents":492379,"sleeping_beauties":137767.0,"sb_rate_pct":27.98,"mean_half_life":11.88,"median_half_life":10.0,"n_patents":305767,"section_name":"Chemistry & Metallurgy"},{"cpc_section":"D","total_patents":48951,"sleeping_beauties":13140.0,"sb_rate_pct":26.843,"mean_half_life":12.28,"median_half_life":11.0,"n_patents":30310,"section_name":"Textiles & Paper"},{"cpc_section":"E","total_patents":131785,"sleeping_beauties":52669.0,"sb_rate_pct":39.966,"mean_half_life":13.74,"median_half_life":12.0,"n_patents":102008,"section_name":"Fixed Constructions"},{"cpc_section":"F","total_patents":358041,"sleeping_beauties":112395.0,"sb_rate_pct":31.392,"mean_half_life":12.78,"median_half_life":11.0,"n_patents":251548,"section_name":"Mechanical Engineering"},{"cpc_section":"G","total_patents":1101851,"sleeping_beauties":256434.0,"sb_rate_pct":23.273,"mean_half_life":9.56,"median_half_life":8.0,"n_patents":739364,"section_name":"Physics"},{"cpc_section":"H","total_patents":1021836,"sleeping_beauties":213622.0,"sb_rate_pct":20.906,"mean_half_life":9.22,"median_half_life":8.0,"n_patents":663892,"section_name":"Electricity"}]